test/__init__.py
test/test_pyrealpro.py
pyrealpro-0.2.0.dist-info/LICENSE.txt
pyrealpro-0.2.0.dist-info/METADATA
pyrealpro-0.2.0.dist-info/WHEEL
pyrealpro-0.2.0.dist-info/top_level.txt
pyrealpro-0.2.0.dist-info/RECORD
