Metadata-Version: 2.1
Name: pyrealpro
Version: 0.2.0
Summary: Tools for building iRealPro songs.
Home-page: https://github.com/splendidtoad/pyrealpro
Author: Andy Chase
Author-email: andychase@gmail.com
License: UNKNOWN
Platform: UNKNOWN
Classifier: Programming Language :: Python :: 3
Classifier: License :: OSI Approved :: MIT License
Classifier: Operating System :: OS Independent
Classifier: Development Status :: 4 - Beta
Classifier: Topic :: Multimedia :: Sound/Audio
Classifier: Topic :: Software Development :: Libraries
Requires-Python: >=3.6
License-File: LICENSE.txt
